utopian/__init__.py
utopian/utopian.py
utopian-0.5.3.dist-info/DESCRIPTION.rst
utopian-0.5.3.dist-info/METADATA
utopian-0.5.3.dist-info/RECORD
utopian-0.5.3.dist-info/WHEEL
utopian-0.5.3.dist-info/entry_points.txt
utopian-0.5.3.dist-info/metadata.json
utopian-0.5.3.dist-info/top_level.txt
