Metadata-Version: 2.0
Name: utopian
Version: 0.5.3
Summary: A CLI for the Utopian.io API.
Home-page: UNKNOWN
Author: amosbastian
Author-email: amosbastian@gmail.com
License: MIT
Keywords: utopian cli
Platform: UNKNOWN
Classifier: Development Status :: 3 - Alpha
Classifier: Intended Audience :: End Users/Desktop
Classifier: License :: OSI Approved :: MIT License
Classifier: Programming Language :: Python :: 2.7
Classifier: Programming Language :: Python :: 3.6
Requires-Dist: Click
Requires-Dist: requests
Requires-Dist: python-dateutil
Requires-Dist: prettytable
